archiver/__init__.py
archiver/__main__.py
archiver/archive.py
archiver/constants.py
archiver/encryption.py
archiver/extract.py
archiver/helpers.py
archiver/integrity.py
archiver/listing.py
archiver/main.py
archiver/preparation_checks.py
archiver/splitter.py
archiver/checks/default_preparation_checks.ini
project_archiver-0.5.0.dist-info/LICENSE
project_archiver-0.5.0.dist-info/METADATA
project_archiver-0.5.0.dist-info/WHEEL
project_archiver-0.5.0.dist-info/entry_points.txt
project_archiver-0.5.0.dist-info/top_level.txt
project_archiver-0.5.0.dist-info/RECORD
