Metadata-Version: 2.1
Name: project-archiver
Version: 0.5.0
Summary: A CLI tool to handle the archiving of large project data.
Home-page: https://github.com/ratschlab/tools-project-archives
Author: Noah Fleischmann
Author-email: noah.fleischmann@inf.ethz.ch
Maintainer: Andre Kahles
Maintainer-email: andre.kahles@inf.ethz.ch
License: MIT license
Keywords: archiving,data lifecycle,research
Classifier: Development Status :: 2 - Pre-Alpha
Classifier: Intended Audience :: Science/Research
Classifier: License :: OSI Approved :: MIT License
Classifier: Natural Language :: English
Classifier: Programming Language :: Python :: 3
Classifier: Programming Language :: Python :: 3.8
Classifier: Programming Language :: Python :: 3.9
License-File: LICENSE
Requires-Dist: multiprocessing-logging<0.4,>=0.3
